Assignments/Assignments 1 and 2 - VHDL Modeling and VHDL Test Bench/rand_num_generator.vhd
-- CPE 487 Spring 2022 Assignment 1: VHDL Modeling
-- Source: https://vhdlguide.readthedocs.io/en/latest/vhdl/dex.html#random-number-generator
-- This is a random number generator implemented using linear feedback shift register (LFSR).
-- 'clockTick.vhd' and 'modMCounter.vhd' are included in the directory as they are required files for this example.

-- rand_num_generator.vhd

-- created by   :   Meher Krishna Patel
-- date                 :   22-Dec-16

-- Feedback polynomial : x^3 + x^2 + 1 
-- maximum length : 2^3 - 1 = 7

-- if generic value is changed,
-- then choose the correct Feedback polynomial i.e. change 'feedback_value' pattern
    
library ieee;
use ieee.std_logic_1164.all;

entity rand_num_generator is
    generic (N :integer := 3);
    port(
        clk, reset  : in std_logic;
        q : out std_logic_vector(N downto 0) -- output of LFSR i.e. random number
    );
end rand_num_generator;

architecture arch of rand_num_generator is
    signal r_reg, r_next : std_logic_vector(N downto 0);
    signal feedback_value : std_logic;  -- based on feedback polynomial
begin
    process(clk, reset)
    begin
        if(reset='1') then
            -- set initial value to '1'. 
            r_reg(0) <= '1'; -- 0th bit = 1
            r_reg(N downto 1) <= (others=>'0'); -- other bits are 0         
        elsif (clk'event and clk='1') then
            r_reg <= r_next; -- otherwise save the next state
        end if;
    end process;
    
    -- N = 3
    -- Feedback polynomial : x^3 + x^2 + 1 
    -- total sequences (maximum) : 2^3 - 1 = 7
    feedback_value <= r_reg(3) xor r_reg(2) xor r_reg(0);
    
    -- N = 4
    -- feedback_value <= r_reg(4) xor r_reg(3) xor r_reg(0);

    -- N = 5, maximum length = 28 (not 31)
    -- feedback_value <= r_reg(5) xor r_reg(3) xor r_reg(0);
    
    -- N = 9 
    -- feedback_value <= r_reg(9) xor r_reg(5) xor r_reg(0);
    
    r_next <= feedback_value & r_reg(N downto 1);
    q <= r_reg;
end arch;

Assignments/Assignments 1 and 2 - VHDL Modeling and VHDL Test Bench/rand_num_generator_tb.vhd
-- CPE 487 Spring 2022 Assignment 2: VHDL Test Bench
-- Calvin Zheng
-- Based on the Simple testbench for half adder (found at https://vhdlguide.readthedocs.io/en/latest/vhdl/testbench.html) as well as example testbench code from dsd/ghdl on GitHub.
-- Plus additional research on testbench clocks

-- rand_num_generator_tb.vhd


library ieee;
use ieee.std_logic_1164.all;


entity rand_num_generator_tb is
    generic (N :integer := 3);
end rand_num_generator_tb;

architecture tb of rand_num_generator_tb is
    signal clk : std_logic := '1'; -- initialize clock
	signal finished : std_logic; -- initialize finish signal to stop clock
	
	signal reset : std_logic; -- inputs
    signal q : std_logic_vector(N downto 0); -- outputs
	
	constant clk_half_period : time := 10 ns;
begin
    -- connecting testbench signals with rand_num_generator.vhd
    UUT : entity work.rand_num_generator port map (clk => clk, reset => reset, q => q);

    clk <= not clk after clk_half_period when finished /= '1' else '0';
    reset <= '1', '0' after 40 ns;
	finished <= '1' after 300 ns;

end tb ;

Assignments/Assignments 1 and 2 - VHDL Modeling and VHDL Test Bench/rand_num_generator_tb.vcd
$date
  Sat Feb 05 23:27:15 2022
$end
$version
  GHDL v0
$end
$timescale
  1 fs
$end
$scope module standard $end
$upscope $end
$scope module std_logic_1164 $end
$upscope $end
$scope module rand_num_generator_tb $end
$var reg 1 ! clk $end
$var reg 1 " finished $end
$var reg 1 # reset $end
$var reg 4 $ q[3:0] $end
$scope module uut $end
$var reg 1 % clk $end
$var reg 1 & reset $end
$var reg 4 ' q[3:0] $end
$var reg 4 ( r_reg[3:0] $end
$var reg 4 ) r_next[3:0] $end
$var reg 1 * feedback_value $end
$upscope $end
$upscope $end
$enddefinitions $end
#0
1!
U"
1#
b0001 $
1%
1&
b0001 '
b0001 (
b1000 )
1*
#10000000
0!
0%
#20000000
1!
1%
#30000000
0!
0%
#40000000
1!
0#
b1000 $
1%
0&
b1000 '
b1000 (
b1100 )
#50000000
0!
0%
#60000000
1!
b1100 $
1%
b1100 '
b1100 (
b0110 )
0*
#70000000
0!
0%
#80000000
1!
b0110 $
1%
b0110 '
b0110 (
b1011 )
1*
#90000000
0!
0%
#100000000
1!
b1011 $
1%
b1011 '
b1011 (
b0101 )
0*
#110000000
0!
0%
#120000000
1!
b0101 $
1%
b0101 '
b0101 (
b0010 )
#130000000
0!
0%
#140000000
1!
b0010 $
1%
b0010 '
b0010 (
b0001 )
#150000000
0!
0%
#160000000
1!
b0001 $
1%
b0001 '
b0001 (
b1000 )
1*
#170000000
0!
0%
#180000000
1!
b1000 $
1%
b1000 '
b1000 (
b1100 )
#190000000
0!
0%
#200000000
1!
b1100 $
1%
b1100 '
b1100 (
b0110 )
0*
#210000000
0!
0%
#220000000
1!
b0110 $
1%
b0110 '
b0110 (
b1011 )
1*
#230000000
0!
0%
#240000000
1!
b1011 $
1%
b1011 '
b1011 (
b0101 )
0*
#250000000
0!
0%
#260000000
1!
b0101 $
1%
b0101 '
b0101 (
b0010 )
#270000000
0!
0%
#280000000
1!
b0010 $
1%
b0010 '
b0010 (
b0001 )
#290000000
0!
0%
#300000000
0!
1"
b0001 $
0%
b0001 '
b0001 (
b1000 )
1*
